alltrees/AVLTree.py
alltrees/BPlusTree.py
alltrees/BTree.py
alltrees/BinarySearchTree.py
alltrees/RedBlack.py
alltrees/__init__.py
alltrees-1.2.4.dist-info/METADATA
alltrees-1.2.4.dist-info/WHEEL
alltrees-1.2.4.dist-info/licenses/LICENSE.txt
alltrees-1.2.4.dist-info/RECORD
