Metadata-Version: 2.1
Name: alltrees
Version: 1.2.4
Summary: A package implementing BST,AVL,Red Black,B-Tree and B+ Tree
Project-URL: Homepage, https://github.com/pypa/sampleproject
Project-URL: Bug Tracker, https://github.com/pypa/sampleproject/issues
Author-email: Madhur Thakkar <madhurthakkar247@gmail.com>, Shantanu Tondlekar <tondlekar88@gmail.com>, Amay Tripathi <amaytripathi16@gmail.com>, Sam Thomas <samthomasv22@gmail.com>
License-File: LICENSE.txt
Classifier: License :: OSI Approved :: MIT License
Classifier: Operating System :: OS Independent
Classifier: Programming Language :: Python :: 3
Requires-Python: >=3.7
